<?xml version="1.0" encoding="utf-8"?>
<ArrayOfProduct xmlns:xsi="http://www.w3.org/2001/XMLSchema-instance" xmlns:xsd="http://www.w3.org/2001/XMLSchema">
  <Product>
    <Id>148</Id>
    <ProductName>פילינג</ProductName>
    <Category>טיפוח_העור</Category>
    <Price>80</Price>
    <QuantityInStock>70</QuantityInStock>
  </Product>
  <Product>
    <Id>149</Id>
    <ProductName>קרם הגנה</ProductName>
    <Category>טיפוח_אישי</Category>
    <Price>70</Price>
    <QuantityInStock>199</QuantityInStock>
  </Product>
  <Product>
    <Id>150</Id>
    <ProductName>סבון</ProductName>
    <Category>טיפוח_עור_הפנים</Category>
    <Price>25</Price>
    <QuantityInStock>13</QuantityInStock>
  </Product>
  <Product>
    <Id>153</Id>
    <ProductName>דבש</ProductName>
    <Category>מוצרי_כוורת</Category>
    <Price>20</Price>
    <QuantityInStock>297</QuantityInStock>
  </Product>
  <Product>
    <Id>161</Id>
    <ProductName>אלוורה</ProductName>
    <Category>משקאות</Category>
    <Price>130</Price>
    <QuantityInStock>0</QuantityInStock>
  </Product>
  <Product>
    <Id>178</Id>
    <ProductName>קרם לחות</ProductName>
    <Category>טיפוח_אישי</Category>
    <Price>50</Price>
    <QuantityInStock>96</QuantityInStock>
  </Product>
  <Product>
    <Id>179</Id>
    <ProductName>סרום</ProductName>
    <Category>משקאות</Category>
    <Price>45</Price>
    <QuantityInStock>66</QuantityInStock>
  </Product>
</ArrayOfProduct>